README.md
setup.py
retroachievements/__init__.py
retroachievements/classes.py
retroachievements/client.py
retroachievements/converters.py
retroachievements/exceptions.py
retroachievements.egg-info/PKG-INFO
retroachievements.egg-info/SOURCES.txt
retroachievements.egg-info/dependency_links.txt
retroachievements.egg-info/requires.txt
retroachievements.egg-info/top_level.txt